django_tracker/__init__.py
django_tracker/_version.py
django_tracker/admin.py
django_tracker/apps.py
django_tracker/constants.py
django_tracker/decorators.py
django_tracker/handles.py
django_tracker/interceptors.py
django_tracker/m2m.py
django_tracker/managers.py
django_tracker/middleware.py
django_tracker/models.py
django_tracker/services.py
django_tracker/urls.py
django_tracker/utils.py
django_tracker/views.py
django_tracker/wrapper.py
django_tracker/migrations/0001_initial.py
django_tracker/migrations/0002_remove_auditlog_django_trac_action_a4b681_idx_and_more.py
django_tracker/migrations/0003_alter_auditlog_object_id.py
django_tracker/migrations/__init__.py
django_tracker/migrations/__pycache__/0001_initial.cpython-310.pyc
django_tracker/migrations/__pycache__/0001_initial.cpython-313.pyc
django_tracker/migrations/__pycache__/0002_remove_auditlog_django_trac_action_a4b681_idx_and_more.cpython-310.pyc
django_tracker/migrations/__pycache__/0002_remove_fields.cpython-313.pyc
django_tracker/migrations/__pycache__/__init__.cpython-310.pyc
django_tracker/migrations/__pycache__/__init__.cpython-313.pyc
django_tracker_unergy-1.2.5.dist-info/licenses/LICENCE
django_tracker_unergy-1.2.5.dist-info/METADATA
django_tracker_unergy-1.2.5.dist-info/WHEEL
django_tracker_unergy-1.2.5.dist-info/top_level.txt
django_tracker_unergy-1.2.5.dist-info/RECORD
