Metadata-Version: 2.4
Name: django-tracker-unergy
Version: 1.2.5
Summary: A Django app for advanced logging capabilities
Author-email: Dmoreno2903 <diegomoreno2903@gmail.com>
Project-URL: Repository, https://gitlab.com/unergy-dev/origination/django-tracker.git
Keywords: django,logging,audit,tracking
Classifier: Environment :: Web Environment
Classifier: Framework :: Django
Classifier: Framework :: Django :: 4.2
Classifier: Intended Audience :: Developers
Classifier: License :: OSI Approved :: MIT License
Classifier: Operating System :: OS Independent
Classifier: Programming Language :: Python
Classifier: Programming Language :: Python :: 3
Classifier: Topic :: Internet :: WWW/HTTP
Classifier: Topic :: Internet :: WWW/HTTP :: Dynamic Content
Classifier: Topic :: Software Development :: Libraries :: Python Modules
Requires-Python: >=3.10.13
License-File: LICENCE
Requires-Dist: Django>=4.2.5
Dynamic: license-file
